spacemake/__init__.py
spacemake/alnstats.py
spacemake/annotator.py
spacemake/cmdline.py
spacemake/config.py
spacemake/contrib.py
spacemake/cutadapt_bam.py
spacemake/errors.py
spacemake/map_strategy.py
spacemake/parallel.py
spacemake/project_df.py
spacemake/quant.py
spacemake/reporting.py
spacemake/smk.py
spacemake/tag_alignments.py
spacemake/unittests.py
spacemake/util.py
spacemake/bin/BamTagHistogram.py
spacemake/bin/fastq_to_uBAM.py
spacemake/data/visium_barcode_positions.csv
spacemake/data/config/config.yaml
spacemake/data/config/longread.yaml
spacemake/data/config/species_data_url.yaml
spacemake/data/puck_collection/create_novaseq_S4_coordinate_system.py
spacemake/data/puck_collection/openst_coordinate_system.csv
spacemake/data/test/test_bc1.csv
spacemake/data/test/test_bc2.csv
spacemake/longread/__main__.py
spacemake/longread/annotation.py
spacemake/longread/cache.py
spacemake/longread/cmdline.py
spacemake/longread/overview.py
spacemake/longread/report.py
spacemake/longread/signature.py
spacemake/preprocess/__init__.py
spacemake/preprocess/cmdline.py
spacemake/preprocess/dge.py
spacemake/preprocess/fastq.py
spacemake/snakemake/__init__.py
spacemake/snakemake/downsample.smk
spacemake/snakemake/dropseq.smk
spacemake/snakemake/longread.smk
spacemake/snakemake/main.smk
spacemake/snakemake/mapping.smk
spacemake/snakemake/merge_samples.smk
spacemake/snakemake/species_init.smk
spacemake/snakemake/variables.py
spacemake/snakemake/visium.smk
spacemake/snakemake/scripts/automated_analysis.py
spacemake/snakemake/scripts/automated_analysis_create_processed_data_files.py
spacemake/snakemake/scripts/automated_analysis_create_report.Rmd
spacemake/snakemake/scripts/clean_top_barcodes.py
spacemake/snakemake/scripts/create_sample_db.R
spacemake/snakemake/scripts/create_sample_overview.Rmd
spacemake/snakemake/scripts/create_spatial_barcode_file.py
spacemake/snakemake/scripts/create_spatial_dge.py
spacemake/snakemake/scripts/filter_mm_reads.py
spacemake-0.8.1.dist-info/COPYING
spacemake-0.8.1.dist-info/LICENSE
spacemake-0.8.1.dist-info/METADATA
spacemake-0.8.1.dist-info/WHEEL
spacemake-0.8.1.dist-info/entry_points.txt
spacemake-0.8.1.dist-info/top_level.txt
spacemake-0.8.1.dist-info/RECORD
