Metadata-Version: 2.1
Name: spacemake
Version: 0.8.1
Summary: A bioinformatic pipeline for the analysis of spatial transcriptomic data
Home-page: https://github.com/rajewsky-lab/spacemake
Author: Tamas Ryszard Sztanka-Toth, Marvin Jens, Nikos Karaiskos, Nikolaus Rajewsky
Author-email: TamasRyszard.Sztanka-Toth@mdc-berlin.de
License: GPL
Project-URL: Bug Tracker, https://github.com/rajewsky-lab/spacemake/issues
Classifier: Programming Language :: Python :: 3
Classifier: License :: OSI Approved :: GNU General Public License v2 or later (GPLv2+)
Classifier: Operating System :: OS Independent
Requires-Python: >=3.8
License-File: LICENSE
License-File: COPYING
